lda_segmenter/__init__.py
lda_segmenter/lda_segmenter.py
lda_segmenter-0.1.1.dist-info/METADATA
lda_segmenter-0.1.1.dist-info/WHEEL
lda_segmenter-0.1.1.dist-info/top_level.txt
lda_segmenter-0.1.1.dist-info/RECORD
