Metadata-Version: 2.1
Name: lda_segmenter
Version: 0.1.1
Summary: 基于LDA主题模型的文档分段工具
Home-page: https://github.com/your_username/lda_segmenter
Author: imuzhangy
Author-email: imuzhangying@gmail.com
Classifier: Programming Language :: Python :: 3
Classifier: License :: OSI Approved :: MIT License
Classifier: Operating System :: OS Independent
Requires-Python: >=3.6
Requires-Dist: jieba
Requires-Dist: python-docx
Requires-Dist: nltk
Requires-Dist: scikit-learn
Requires-Dist: numpy
